asyncqiwi/__init__.py
asyncqiwi/__version__.py
asyncqiwi/asyncqiwi.py
asyncqiwi/exceptions.py
asyncqiwi/utils.py
asyncqiwi/types/__init__.py
asyncqiwi/types/p2p.py
tests/__init__.py
tests/test.py
asyncqiwi-0.1.0.dist-info/LICENSE
asyncqiwi-0.1.0.dist-info/METADATA
asyncqiwi-0.1.0.dist-info/WHEEL
asyncqiwi-0.1.0.dist-info/top_level.txt
asyncqiwi-0.1.0.dist-info/RECORD
